now_lms/__init__.py
now_lms/version.py
now_lms-0.0.1.dev20211012.dist-info/METADATA
now_lms-0.0.1.dev20211012.dist-info/WHEEL
now_lms-0.0.1.dev20211012.dist-info/entry_points.txt
now_lms-0.0.1.dev20211012.dist-info/top_level.txt
now_lms-0.0.1.dev20211012.dist-info/RECORD
